CHANGELOG.txt
LICENCE.txt
MANIFEST.in
README.txt
setup.py
OwnPackage/__init__.py
OwnPackage.egg-info/PKG-INFO
OwnPackage.egg-info/SOURCES.txt
OwnPackage.egg-info/dependency_links.txt
OwnPackage.egg-info/top_level.txt