Metadata-Version: 1.1
Name: OwnPackage
Version: 0.0.1
Summary: This is a library which calculates the rank by given data.
Home-page: UNKNOWN
Author: Roushan Singh
Author-email: rsingh3_be18@thapar.edu
License: MIT
Keywords: Topsis
Platform: UNKNOWN
Classifier: Development Status :: 5 - Production/Stable
Classifier: Intended Audience :: Education
Classifier: Operating System :: Microsoft :: Windows :: Windows 10
Classifier: License :: OSI Approved :: MIT License
Classifier: Programming Language :: Python :: 3
